jott/__init__.py
jott-0.0.dist-info/DESCRIPTION.rst
jott-0.0.dist-info/METADATA
jott-0.0.dist-info/RECORD
jott-0.0.dist-info/WHEEL
jott-0.0.dist-info/metadata.json
jott-0.0.dist-info/top_level.txt
