Metadata-Version: 2.0
Name: jott
Version: 0.0
Summary: jott
Home-page: https://github.com/hkmshb/jott.git
Author: Abdul-Hakeem Shaibu
Author-email: hkmshb@gmail.com
License: UNKNOWN
Keywords: note editor
Platform: any
Classifier: Development Status :: 1 - Planning
Classifier: Intended Audience :: Developers
Classifier: Natural Language :: English
Classifier: License :: OSI Approved :: BSD License
Classifier: Operating System :: OS Independent
Classifier: Programming Language :: Python :: 3.6
Provides-Extra: test
Requires-Dist: pytest; extra == 'test'
Requires-Dist: pytest-cov; extra == 'test'
